{
    "task_id": "00004:316",
    "response": "The image contains the following objects:\n\n1. A blue horizontal bar.\n2. A black circular object.\n3. A green spherical object.\n\nHere is the position of these objects in JSON format:\n\n```json\n[\n    {\"bbox_2d\": [0, 186, 159, 194], \"label\": \"blue horizontal bar\"},\n    {\"bbox_2d\": [37, 252, 55, 277], \"label\": \"black circular object\"},\n    {\"bbox_2d\": [108, 1, 134, 25], \"label\": \"green spherical object\"}\n]\n```\n\nNote: The exact coordinates might need to be adjusted based on the actual dimensions and resolution of the image.<|im_end|>",
    "output_json": "The image contains the following objects:\n\n1. A blue horizontal bar.\n2. A black circular object.\n3. A green spherical object.\n\nHere is the position of these objects in JSON format:\n\n```json\n[\n    {\"bbox_2d\": [0, 186, 159, 194], \"label\": \"blue horizontal bar\"},\n    {\"bbox_2d\": [37, 252, 55, 277], \"label\": \"black circular object\"},\n    {\"bbox_2d\": [108, 1, 134, 25], \"label\": \"green spherical object\"}\n]\n```\n\nNote: The exact coordinates might need to be adjusted based on the actual dimensions and resolution of the image.<|im_end|>"
}