{
    "task_id": "00009:672",
    "response": "The image contains the following elements:\n\n1. A vertical black line.\n2. A horizontal black line that intersects with the vertical line at a right angle.\n3. A blue horizontal line at the bottom of the image.\n\nHere is the JSON representation of the positions of these objects:\n\n```json\n[\n    {\"bbox_2d\": [0, 0, 308, 308], \"label\": \"black vertical line\"},\n    {\"bbox_2d\": [156, 149, 308, 170], \"label\": \"black horizontal line\"},\n    {\"bbox_2d\": [0, 308, 308, 308], \"label\": \"blue horizontal line\"}\n]\n```\n\nNote: The coordinates are relative to the image's boundaries, where the top-left corner is (0, 0) and the bottom-right corner is (308, 308).<|im_end|>",
    "output_json": "The image contains the following elements:\n\n1. A vertical black line.\n2. A horizontal black line that intersects with the vertical line at a right angle.\n3. A blue horizontal line at the bottom of the image.\n\nHere is the JSON representation of the positions of these objects:\n\n```json\n[\n    {\"bbox_2d\": [0, 0, 308, 308], \"label\": \"black vertical line\"},\n    {\"bbox_2d\": [156, 149, 308, 170], \"label\": \"black horizontal line\"},\n    {\"bbox_2d\": [0, 308, 308, 308], \"label\": \"blue horizontal line\"}\n]\n```\n\nNote: The coordinates are relative to the image's boundaries, where the top-left corner is (0, 0) and the bottom-right corner is (308, 308).<|im_end|>"
}