{
    "task_id": "00010:474",
    "response": "The image contains the following objects:\n\n1. A blue line that appears to be a wall.\n2. A green circle that looks like a ball.\n3. A black platform.\n\nHere is the position of these objects in JSON format:\n\n```json\n[\n    {\"bbox_2d\": [0, 185, 476, 364], \"label\": \"black platform\"},\n    {\"bbox_2d\": [19, 19, 100, 100], \"label\": \"green circle\"},\n    {\"bbox_2d\": [0, 0, 476, 364], \"label\": \"blue line\"}\n]\n```\n\nNote: The coordinates are relative to the image's top-left corner, with the origin at (0, 0). The exact coordinates would depend on the specific dimensions and resolution of the image.<|im_end|>",
    "output_json": "The image contains the following objects:\n\n1. A blue line that appears to be a wall.\n2. A green circle that looks like a ball.\n3. A black platform.\n\nHere is the position of these objects in JSON format:\n\n```json\n[\n    {\"bbox_2d\": [0, 185, 476, 364], \"label\": \"black platform\"},\n    {\"bbox_2d\": [19, 19, 100, 100], \"label\": \"green circle\"},\n    {\"bbox_2d\": [0, 0, 476, 364], \"label\": \"blue line\"}\n]\n```\n\nNote: The coordinates are relative to the image's top-left corner, with the origin at (0, 0). The exact coordinates would depend on the specific dimensions and resolution of the image.<|im_end|>"
}