{
    "task_id": "00015:457",
    "response": "The image contains the following elements:\n\n1. A green sphere.\n2. A black rectangular platform.\n3. A blue horizontal line at the bottom.\n\nHere is the position of these objects in JSON format:\n\n```json\n[\n    {\"bbox_2d\": [40, 135, 67, 158], \"label\": \"green sphere\"},\n    {\"bbox_2d\": [29, 158, 70, 170], \"label\": \"black platform\"},\n    {\"bbox_2d\": [0, 300, 140, 305], \"label\": \"blue horizontal line\"}\n]\n```\n\nNote: The exact coordinates depend on the scale and resolution of the image, but this JSON provides the relative positions of the objects as described.<|im_end|>",
    "output_json": "The image contains the following elements:\n\n1. A green sphere.\n2. A black rectangular platform.\n3. A blue horizontal line at the bottom.\n\nHere is the position of these objects in JSON format:\n\n```json\n[\n    {\"bbox_2d\": [40, 135, 67, 158], \"label\": \"green sphere\"},\n    {\"bbox_2d\": [29, 158, 70, 170], \"label\": \"black platform\"},\n    {\"bbox_2d\": [0, 300, 140, 305], \"label\": \"blue horizontal line\"}\n]\n```\n\nNote: The exact coordinates depend on the scale and resolution of the image, but this JSON provides the relative positions of the objects as described.<|im_end|>"
}