{
    "task_id": "00024:552",
    "response": "The image contains the following objects:\n\n1. A blue object at the bottom.\n2. A green ball above the blue object.\n3. A black platform below the green ball.\n\nHere is the position of these objects in JSON format:\n\n```json\n[\n    {\"bbox_2d\": [0, 284, 336, 336], \"label\": \"blue object\"},\n    {\"bbox_2d\": [157, 29, 183, 55], \"label\": \"green ball\"},\n    {\"bbox_2d\": [0, 196, 336, 240], \"label\": \"black platform\"}\n]\n```\n\nNote: The exact coordinates depend on the scale and resolution of the image, but this JSON provides the relative positions of the objects as described.<|im_end|>",
    "output_json": "The image contains the following objects:\n\n1. A blue object at the bottom.\n2. A green ball above the blue object.\n3. A black platform below the green ball.\n\nHere is the position of these objects in JSON format:\n\n```json\n[\n    {\"bbox_2d\": [0, 284, 336, 336], \"label\": \"blue object\"},\n    {\"bbox_2d\": [157, 29, 183, 55], \"label\": \"green ball\"},\n    {\"bbox_2d\": [0, 196, 336, 240], \"label\": \"black platform\"}\n]\n```\n\nNote: The exact coordinates depend on the scale and resolution of the image, but this JSON provides the relative positions of the objects as described.<|im_end|>"
}